dramatiq_apscheduler/__init__.py
dramatiq_apscheduler/main.py
dramatiq_apscheduler-0.2.1.dist-info/LICENSE
dramatiq_apscheduler-0.2.1.dist-info/METADATA
dramatiq_apscheduler-0.2.1.dist-info/WHEEL
dramatiq_apscheduler-0.2.1.dist-info/entry_points.txt
dramatiq_apscheduler-0.2.1.dist-info/top_level.txt
dramatiq_apscheduler-0.2.1.dist-info/RECORD
