Metadata-Version: 2.1
Name: dramatiq-apscheduler
Version: 0.2.1
Summary: UNKNOWN
Home-page: https://github.com/MightySCollins/dramatiq-apscheduler/
Author: Sam Collins
License: MIT
Platform: UNKNOWN
Classifier: License :: OSI Approved :: MIT License
Classifier: Programming Language :: Python :: 3
Classifier: Programming Language :: Python :: 3.7
Requires-Dist: Click
Requires-Dist: pyyaml
Requires-Dist: apscheduler
Requires-Dist: dramatiq
Requires-Dist: pytz
Requires-Dist: pika
Requires-Dist: redis
Requires-Dist: python-redis-lock
